tah_data.py
tah_data-1.2.0.dist-info/METADATA
tah_data-1.2.0.dist-info/WHEEL
tah_data-1.2.0.dist-info/RECORD
