Metadata-Version: 2.1
Name: tah-data
Version: 1.2.0
Summary: 
Author: Ahmed Sherif
Requires-Python: >=3.8,<3.12
Classifier: Programming Language :: Python :: 3
Classifier: Programming Language :: Python :: 3.8
Classifier: Programming Language :: Python :: 3.9
Classifier: Programming Language :: Python :: 3.10
Classifier: Programming Language :: Python :: 3.11
Requires-Dist: boto3 (>=1.26.158,<2.0.0)
Requires-Dist: dvc (>=3.1.0,<4.0.0)
Requires-Dist: dvc-s3 (>=2.23.0,<3.0.0)
Requires-Dist: pre-commit (>=3.3.2,<4.0.0)
